pyjs_bridge/__init__.py
pyjs_bridge/pyjs_bridge.py
python_js_bridge-0.dist-info/LICENSE
python_js_bridge-0.dist-info/METADATA
python_js_bridge-0.dist-info/WHEEL
python_js_bridge-0.dist-info/top_level.txt
python_js_bridge-0.dist-info/RECORD
