Metadata-Version: 2.1
Name: python_js_bridge
Version: 0
Summary: A bridge between Python and JavaScript
Home-page: https://github.com/qaqFei/pyjs_bridge
Author: qaqFei
Author-email: qaq_fei@163.com
License: MIT License
Classifier: Programming Language :: Python :: 3.12
Classifier: License :: OSI Approved :: MIT License
Classifier: Operating System :: Microsoft :: Windows
Requires-Python: >=3.12.0
License-File: LICENSE
